README.md
setup.cfg
setup.py
kinsumer/__init__.py
kinsumer/__main__.py
kinsumer/bucket.py
kinsumer/checkpointer.py
kinsumer/cli.py
kinsumer/config.py
kinsumer/consumer.py
kinsumer/ctx.py
kinsumer/globals.py
kinsumer/heartbeat.py
kinsumer/helpers.py
kinsumer/logging.py
kinsumer/streams.py
kinsumer/version.py
kinsumer.egg-info/PKG-INFO
kinsumer.egg-info/SOURCES.txt
kinsumer.egg-info/dependency_links.txt
kinsumer.egg-info/entry_points.txt
kinsumer.egg-info/not-zip-safe
kinsumer.egg-info/requires.txt
kinsumer.egg-info/top_level.txt
tests/__init__.py
tests/conftest.py
tests/examples.py
tests/test_config.py