Metadata-Version: 1.1
Name: kinsumer
Version: 0.5.3
Summary: High level Amazon Kinesis Streams consumer
Home-page: UNKNOWN
Author: Ungi Kim
Author-email: ungi@ungikim.me
License: UNKNOWN
Platform: UNKNOWN
Classifier: Development Status :: 3 - Alpha
Classifier: Environment :: No Input/Output (Daemon)
Classifier: Intended Audience :: Developers
Classifier: Programming Language :: Python :: 3 :: Only
Classifier: Programming Language :: Python :: 3.6
Classifier: Topic :: Software Development :: Libraries :: Python Modules
